CHANGELOG.md
LICENSE
MANIFEST.in
README.md
setup.cfg
setup.py
SRMspinanalysis/__init__.py
SRMspinanalysis/_version.py
SRMspinanalysis/get_data.py
SRMspinanalysis/model.py
SRMspinanalysis/plot.py
SRMspinanalysis/sizing.py
SRMspinanalysis/solver.py
SRMspinanalysis.egg-info/PKG-INFO
SRMspinanalysis.egg-info/SOURCES.txt
SRMspinanalysis.egg-info/dependency_links.txt
SRMspinanalysis.egg-info/not-zip-safe
SRMspinanalysis.egg-info/requires.txt
SRMspinanalysis.egg-info/top_level.txt
SRMspinanalysis/tests/__init__.py
SRMspinanalysis/tests/test_get_data.py
SRMspinanalysis/tests/test_sizing.py
SRMspinanalysis/tests/test_solver.py