Metadata-Version: 1.2
Name: SRMspinanalysis
Version: 0.1.0
Summary: Spin-stabilization Analysis for Solid Rocket Motor Systems
Home-page: https://github.com/SoftwareDevEngResearch/SRMspinanalysis
Author: Matthew D. Morse
Author-email: morse.mattd@gmail.com
License: MIT
Platform: UNKNOWN
Classifier: License :: OSI Approved :: MIT License
Classifier: Intended Audience :: Developers
Classifier: Intended Audience :: Science/Research
Classifier: Natural Language :: English
Classifier: Programming Language :: Python :: 2
Requires-Python: >=2
